scs_test_package_eugenerrr/__init__.py
scs_test_package_eugenerrr/example.py
scs_test_package_eugenerrr-0.0.15.dist-info/METADATA
scs_test_package_eugenerrr-0.0.15.dist-info/WHEEL
scs_test_package_eugenerrr-0.0.15.dist-info/top_level.txt
scs_test_package_eugenerrr-0.0.15.dist-info/RECORD
