Metadata-Version: 2.4
Name: scs_test_package_eugenerrr
Version: 0.0.15
Summary: Test project
Author-email: Whatever <mail@gmail.com>
Project-URL: Homepage, https://github.com/eugenebmx/scs_test_package_eugenerrr
Classifier: Programming Language :: Python :: 3
Classifier: License :: OSI Approved :: MIT License
Classifier: Operating System :: OS Independent
Requires-Python: >3.6
